end2endML/__init__.py
end2endML/automate_analysis.py
end2endML/automate_modeling_evaluation.py
end2endML/preprocessing.py
end2endML/utilities.py
end2endML/version.py
end2endML/evaluate_models/__init__.py
end2endML/evaluate_models/classification_metrics.py
end2endML/evaluate_models/regression_metrics.py
end2endML/select_fit_models/__init__.py
end2endML/select_fit_models/classification_models.py
end2endML/select_fit_models/imbalanced_classification_models.py
end2endML/select_fit_models/regression_models.py
end2endML-0.9.3.dist-info/LICENSE.txt
end2endML-0.9.3.dist-info/METADATA
end2endML-0.9.3.dist-info/WHEEL
end2endML-0.9.3.dist-info/top_level.txt
end2endML-0.9.3.dist-info/RECORD
