Metadata-Version: 2.1
Name: end2endML
Version: 0.9.3
Summary: Automated data analysis pipelines on tabular data for data analyst
Home-page: https://gitlab.com/YipengUva/end2endml_pkg
Author: Yipeng Song
Author-email: yipeng.song@hotmail.com
License: UNKNOWN
Project-URL: Bug Tracker, https://gitlab.com/YipengUva/end2endml_pkg/issues
Keywords: data analysis,machine learning,automation
Platform: UNKNOWN
Classifier: Development Status :: 4 - Beta
Classifier: Programming Language :: Python :: 3
Classifier: License :: OSI Approved :: MIT License
Classifier: Operating System :: OS Independent
Classifier: Topic :: Scientific/Engineering :: Artificial Intelligence
Requires-Python: >=3.6, <4
License-File: LICENSE.txt
Requires-Dist: numpy (>=1.19)
Requires-Dist: pandas (>=1.1)
Requires-Dist: imbalanced-learn (>=0.8.1)
Requires-Dist: scikit-learn (>=1.0)
Requires-Dist: pandas-profiling (>=2.9.0)
Requires-Dist: joblib (>=1.0)
Requires-Dist: xgboost (>=1.4)
Requires-Dist: optuna (>=2.7)
